{
  "$schema": "https://json-schema.org/draft/2020-12/schema",
  "$id": "sie://schemas/gsm/v1/Mechanism.schema.json",
  "title": "Mechanism (GSM base archetype)",
  "description": "Base ascription schema for Mechanism ElementDefinitions. Defines the logical causal unit's behavioral attributes and identifies the owning Structure via structureId. Effector/Receptor ports are derived by the definition-manager from the Mechanism operation (they are not user-authored ascription fields). Tenant-defined archetypes extending Mechanism MUST reference this schema via allOf.",
  "$gsm:sealed": true,
  "$gsm:elementDefinitionSubtype": "Mechanism",
  "type": "object",
  "required": [
    "structureId",
    "function",
    "operation",
    "operationLanguage"
  ],
  "properties": {
    "structureId": {
      "type": "string",
      "minLength": 1,
      "description": "Identifier of the owning Structure (typically the Structure ElementDefinition's elementId)."
    },
    "function": {
      "type": "string",
      "minLength": 1,
      "description": "Capability label describing what the Mechanism does (e.g., 'validation', 'routing', 'transformation')."
    },
    "operation": {
      "type": "string",
      "minLength": 1,
      "description": "Executable logic in the declared operationLanguage. Encodes what the Mechanism does — behavioral definition."
    },
    "operationLanguage": {
      "type": "string",
      "enum": [
        "STARLARK"
      ],
      "description": "Expression language for the operation field. Currently only STARLARK (Python-like, for behavioral logic)."
    }
  },
  "additionalProperties": false
}