{
  "$schema": "http://json-schema.org/draft-07/schema#",
  "$id": "sie://schemas/gsm/v1/Sensing.json",
  "title": "Sensing (GSM v1)",
  "description": "The microscopic homeostatic verification primitive: links an Actuation to its feedback observation, forming a per-actuation closed-loop between Actuator and Sensor. Only exists for closed-loop actuations (return-value-assignment in Rule body).",
  "allOf": [
    {
      "$ref": "sie://schemas/gsm/v1/SystemicPrimitiveDefinition.json"
    }
  ],
  "type": "object",
  "required": [
    "actuation"
  ],
  "properties": {
    "actuation": {
      "$ref": "sie://schemas/gsm/v1/common.json#/definitions/UUID",
      "description": "Reference to the Actuation observed by this Sensing."
    }
  },
  "x-sie-derived": {
    "sensor": {
      "description": "Back-reference to auto-derived Sensor mechanism.",
      "derivedFrom": "Rule body → sys.* return-value-assignment → Sensing derivation"
    },
    "actuationEventArchetype": {
      "description": "EventArchetype of the ActuationEvent (Actuator → Sensor flow, cybernetic step 4).",
      "derivedFrom": "Actuation → Actuator.Effector.emittedEventArchetype"
    },
    "actuationSensingEventArchetype": {
      "description": "EventArchetype of the ActuationSensingEvent (Sensor → Controller flow, cybernetic step 6).",
      "derivedFrom": "Sensing derivation → auto-defined ActuationSensingEvent archetype"
    },
    "sensingReceptor": {
      "description": "Controller's Receptor that receives the ActuationSensingEvent, closing the loop.",
      "derivedFrom": "Rule body → return-value-assignment → Controller sensingReceptor derivation"
    }
  }
}